uf3/__init__.py
uf3/data/__init__.py
uf3/data/analyze.py
uf3/data/composition.py
uf3/data/geometry.py
uf3/data/io.py
uf3/forcefield/__init__.py
uf3/forcefield/calculator.py
uf3/forcefield/lammps.py
uf3/forcefield/properties/__init__.py
uf3/forcefield/properties/elastic.py
uf3/forcefield/properties/phonon.py
uf3/regression/__init__.py
uf3/regression/least_squares.py
uf3/regression/regularize.py
uf3/representation/__init__.py
uf3/representation/angles.py
uf3/representation/bspline.py
uf3/representation/distances.py
uf3/representation/process.py
uf3/util/__init__.py
uf3/util/cubehelix.py
uf3/util/json_io.py
uf3/util/parallel.py
uf3/util/plot_slices_3b.py
uf3/util/plotting.py
uf3/util/plotting3d.py
uf3/util/subsample.py
uf3/util/user_config.py
uf3-0.4.0.dist-info/LICENSE
uf3-0.4.0.dist-info/METADATA
uf3-0.4.0.dist-info/WHEEL
uf3-0.4.0.dist-info/top_level.txt
uf3-0.4.0.dist-info/RECORD
