Metadata-Version: 2.1
Name: uf3
Version: 0.4.0
Summary: Ultra-Fast Force Fields for molecular dynamics
Home-page: https://github.com/uf3/uf3
Author: Stephen R. Xie, Matthias Rupp
Author-email: sxiexie@ufl.edu
License: Apache 2.0
Classifier: Programming Language :: Python :: 3.7
Classifier: Development Status :: 3 - Alpha
Classifier: Intended Audience :: Science/Research
Classifier: Operating System :: OS Independent
Classifier: Topic :: Scientific/Engineering
License-File: LICENSE
Requires-Dist: ase
Requires-Dist: matplotlib
Requires-Dist: ndsplines
Requires-Dist: numba
Requires-Dist: numpy
Requires-Dist: pandas
Requires-Dist: plotly
Requires-Dist: PyYAML
Requires-Dist: scikit-learn
Requires-Dist: scipy
Requires-Dist: tables
Requires-Dist: tqdm
Provides-Extra: elastic_constants
Requires-Dist: elastic ; extra == 'elastic_constants'
Provides-Extra: phonon_spectra
Requires-Dist: phonopy >=2.6.0 ; extra == 'phonon_spectra'
Requires-Dist: seekpath ; extra == 'phonon_spectra'
Requires-Dist: spglib ; extra == 'phonon_spectra'
